mypiprandomdata/__init__.py
mypiprandomdata/cli.py
mypiprandomdata/data/Cities.txt
mypiprandomdata/data/FirstName.txt
mypiprandomdata/data/LastName.txt
mypiprandomdata/data/Real_Address.txt
mypiprandomdata/data/States.txt
mypiprandomdata/data/UserAgent.txt
mypiprandomdata/data/ZipCode.txt
mypiprandomdata/data/data.json
mypiprandomdata-0.8.5.dist-info/METADATA
mypiprandomdata-0.8.5.dist-info/WHEEL
mypiprandomdata-0.8.5.dist-info/entry_points.txt
mypiprandomdata-0.8.5.dist-info/top_level.txt
mypiprandomdata-0.8.5.dist-info/RECORD
