Metadata-Version: 2.1
Name: mypiprandomdata
Version: 0.8.5
Summary: A package to generate random data.
Home-page: https://github.com/spat959/mypiprandomdata
Author: Inzmamul Haq
Author-email: spat959@gmail.com
Keywords: random data generator
